{
    "高二上第四課": {
        "joylous": "令人愉快的",
        "joyful": "令人愉快的",
        "accompany": "陪伴",
        "company": "陪伴",
        "essential": "本質的；基本的 or 必要的；極其重要的 ",
        "concept": "概念",
        "mourn": "哀悼",
        "mournful": "悲傷的",
        "sorrow": "悲傷",
        "sorrowful": "悲傷的",
        "occasion": "場合",
        "occasional": "偶爾的",
        "reunion": "重逢；團聚",
        "reunite": "重逢；重聚",
        "anticipate": "期盼",
        "anticipation": "預料",
        "arrival": "到達；到來",
        "restore": "修補；整修",
        "preference": "偏愛",
        "prefer": "偏愛",
        "reception": "歡迎",
        "receptionist": "接待員",
        "feast": "宴會",
        "dawn": "黎明；破曉",
        "transform": "使…改變型態",
        "transformation": "轉變",
        "resemble": "看起來像",
        "resemblance": "相似；相像",
        "participate": "參加",
        "participation": "參加；參與",
        "mock": "虛假的；不誠實的",
        "recognize": "承認；意識到；體認到 or 認出；辨識出",
        "recognition": "承認",
        "inevitable": "不可避免的",
        "cycle": "循環",
        "await": "等待",
        "escape": "避免 or 逃跑；逃走"
    },
    "高二上第五課": {
        "blossom": "花朵；開花",
        "splendor": "壯麗；雄偉",
        "splendid": "壯麗的；雄偉的 or 非常好的",
        "previously": "先前地",
        "previous": "先前的",
        "capital": "首都 or 資本；資金",
        "boast": "以..為傲；擁有",
        "historic": "歷史悠久的；歷史上著名的",
        "historical": "歷史的",
        "historian": "歷史學家",
        "landmark": "地標",
        "entrace": "大門；入口",
        "magnificent": "壯麗的；雄偉的 ",
        "breathtaking": "驚人的；極為美麗的",
        "leisurely": "悠閒的",
        "leisure": "閒暇",
        "stunning": "撼動人心的；令人驚訝的",
        "stun": "使驚訝 or 使印象深刻",
        "delicate": "纖細的；精美的",
        "delicacy": "纖細；精美 or 佳餚；美食",
        "distinctive": "獨特的",
        "distinction": "差別",
        "distinct": "顯著的；明顯的",
        "appearence": "外表",
        "appear": "出現",
        "instrument": "樂器 or 工具；儀器",
        "instrumental": "樂器的",
        "literature": "文學；文學作品",
        "literary": "文學的；文藝的",
        "deliberate": "小心翼翼的 or 有意的:故意的",
        "graceful": "優美的；優雅的",
        "grace": "優美；優雅",
        "destination": "目的地"
    }
}